pyzendesk/__init__.py
pyzendesk/admins.py
pyzendesk/agents.py
pyzendesk/api.py
pyzendesk/attachments.py
pyzendesk/constants.py
pyzendesk/tickets.py
pyzendesk/users.py
pyzendesk/samples/__init__.py
pyzendesk/samples/admins.py
pyzendesk/samples/agents.py
pyzendesk/samples/me.py
pyzendesk/samples/tickets.py
pyzendesk/samples/users.py
pyzendesk-0.5.0.dist-info/licenses/LICENSE
pyzendesk-0.5.0.dist-info/METADATA
pyzendesk-0.5.0.dist-info/WHEEL
pyzendesk-0.5.0.dist-info/top_level.txt
pyzendesk-0.5.0.dist-info/RECORD
