Metadata-Version: 2.4
Name: PyZendesk
Version: 0.5.0
Summary: API for Zendesk
Home-page: http://www.muflone.com/pyzendesk/
Author: Fabio Castelli
Author-email: muflone@muflone.com
License: GPLv3+
Classifier: Development Status :: 1 - Planning
Classifier: Intended Audience :: Developers
Classifier: License :: OSI Approved :: GNU General Public License v3 or later (GPLv3+)
Classifier: Operating System :: OS Independent
Classifier: Programming Language :: Python :: 3
Classifier: Programming Language :: Python :: 3.9
Classifier: Programming Language :: Python :: 3.10
Classifier: Programming Language :: Python :: 3.11
Classifier: Programming Language :: Python :: 3.12
Classifier: Programming Language :: Python :: 3.13
Classifier: Topic :: Software Development :: Libraries :: Python Modules
License-File: LICENSE
Requires-Dist: requests~=2.28
Dynamic: license-file
